chemlib/__init__.py
chemlib/chemistry.py
chemlib/constants.py
chemlib/electrochemistry.py
chemlib/parse.py
chemlib/quantum_mechanics.py
chemlib/thermochemistry.py
chemlib/utils.py
chemlib/resources/PTE.csv
chemlib/resources/gcell_root.png
chemlib/resources/thermochemistry.csv
chemlib-2.2.4.dist-info/AUTHORS
chemlib-2.2.4.dist-info/LICENSE.txt
chemlib-2.2.4.dist-info/METADATA
chemlib-2.2.4.dist-info/WHEEL
chemlib-2.2.4.dist-info/top_level.txt
chemlib-2.2.4.dist-info/RECORD
