Metadata-Version: 2.1
Name: chemlib
Version: 2.2.4
Summary: An easy-to-use library that quickly performs chemistry calculations.
Home-page: https://github.com/harirakul/chemlib
Download-URL: https://pypi.org/project/chemlib/
Author: Hari Ambethkar
Author-email: harirakul.a@gmail.com
License: MIT
Keywords: Chemistry,Chemlib
License-File: LICENSE.txt
License-File: AUTHORS
